{
	"info": {
		"_postman_id": "82fae4e9-fa0f-4055-a38e-17a395c6f934",
		"name": "Group_19_HomeWork1",
		"schema": "https://schema.getpostman.com/json/collection/v2.1.0/collection.json"
	},
	"item": [
		{
			"name": "Log In",
			"request": {
				"method": "POST",
				"header": [],
				"url": {
					"raw": "http://116.203.27.46:5002/login?login=Sanya&password=qwe",
					"protocol": "http",
					"host": [
						"116",
						"203",
						"27",
						"46"
					],
					"port": "5002",
					"path": [
						"login"
					],
					"query": [
						{
							"key": "login",
							"value": "Sanya"
						},
						{
							"key": "password",
							"value": "qwe"
						}
					]
				}
			},
			"response": []
		},
		{
			"name": "User_info",
			"request": {
				"method": "POST",
				"header": [],
				"body": {
					"mode": "raw",
					"raw": "{\r\n    \"age\": 33,\r\n    \"salary\": 1000,\r\n    \"name\": \"Sanya\",\r\n    \"auth_token\": \"/s34lfgbj/None/jjd909/58794kjkWpqc4676None317535evny\"\r\n}",
					"options": {
						"raw": {
							"language": "json"
						}
					}
				},
				"url": {
					"raw": "http://116.203.27.46:5002/user_info?age=33&salary=1000&name=Sanya&auth_token=\"/s34lfgbj/None/jjd909/58794kjkWpqc4676None317535evny\"",
					"protocol": "http",
					"host": [
						"116",
						"203",
						"27",
						"46"
					],
					"port": "5002",
					"path": [
						"user_info"
					],
					"query": [
						{
							"key": "age",
							"value": "33"
						},
						{
							"key": "salary",
							"value": "1000"
						},
						{
							"key": "name",
							"value": "Sanya"
						},
						{
							"key": "auth_token",
							"value": "\"/s34lfgbj/None/jjd909/58794kjkWpqc4676None317535evny\""
						}
					]
				}
			},
			"response": []
		},
		{
			"name": "New_data",
			"request": {
				"method": "POST",
				"header": [],
				"body": {
					"mode": "formdata",
					"formdata": [
						{
							"key": "age",
							"value": "33",
							"type": "text"
						},
						{
							"key": "salary",
							"value": "1000",
							"type": "text"
						},
						{
							"key": "name",
							"value": "Sanya",
							"type": "text"
						},
						{
							"key": "auth_token",
							"value": "\"/s34lfgbj/None/jjd909/70545kjkWpqc3406None253300evny\"",
							"type": "text"
						}
					],
					"options": {
						"raw": {
							"language": "json"
						}
					}
				},
				"url": {
					"raw": "http://116.203.27.46:5002/new_data",
					"protocol": "http",
					"host": [
						"116",
						"203",
						"27",
						"46"
					],
					"port": "5002",
					"path": [
						"new_data"
					]
				}
			},
			"response": []
		},
		{
			"name": "Test_pet_info",
			"request": {
				"method": "POST",
				"header": [],
				"body": {
					"mode": "formdata",
					"formdata": [
						{
							"key": "age",
							"value": "33",
							"type": "text"
						},
						{
							"key": "weight",
							"value": "75",
							"type": "text"
						},
						{
							"key": "name",
							"value": "Sanya",
							"type": "text"
						},
						{
							"key": "auth_token",
							"value": "\"/s34lfgbj/None/jjd909/58794kjkWpqc4676None317535evny\"",
							"type": "text"
						}
					]
				},
				"url": {
					"raw": "http://116.203.27.46:5002/test_pet_info?age=33&weight=75&name=Sanya&auth_token=\"/s34lfgbj/None/jjd909/58794kjkWpqc4676None317535evny\"",
					"protocol": "http",
					"host": [
						"116",
						"203",
						"27",
						"46"
					],
					"port": "5002",
					"path": [
						"test_pet_info"
					],
					"query": [
						{
							"key": "age",
							"value": "33"
						},
						{
							"key": "weight",
							"value": "75"
						},
						{
							"key": "name",
							"value": "Sanya"
						},
						{
							"key": "auth_token",
							"value": "\"/s34lfgbj/None/jjd909/58794kjkWpqc4676None317535evny\""
						}
					]
				}
			},
			"response": []
		},
		{
			"name": "Get_test_user",
			"request": {
				"method": "POST",
				"header": [],
				"body": {
					"mode": "formdata",
					"formdata": [
						{
							"key": "age",
							"value": "33",
							"type": "text"
						},
						{
							"key": "salary",
							"value": "1000",
							"type": "text"
						},
						{
							"key": "name",
							"value": "Sanya",
							"type": "text"
						},
						{
							"key": "auth_token",
							"value": "\"/s34lfgbj/None/jjd909/70545kjkWpqc3406None253300evny\"",
							"type": "text"
						}
					]
				},
				"url": {
					"raw": "http://116.203.27.46:5002/get_test_user",
					"protocol": "http",
					"host": [
						"116",
						"203",
						"27",
						"46"
					],
					"port": "5002",
					"path": [
						"get_test_user"
					]
				}
			},
			"response": []
		},
		{
			"name": "Currency",
			"request": {
				"method": "POST",
				"header": [],
				"body": {
					"mode": "formdata",
					"formdata": [
						{
							"key": "auth_token",
							"value": "\"/s34lfgbj/None/jjd909/70545kjkWpqc3406None253300evny\"",
							"type": "text"
						}
					]
				},
				"url": {
					"raw": "http://116.203.27.46:5002/currency",
					"protocol": "http",
					"host": [
						"116",
						"203",
						"27",
						"46"
					],
					"port": "5002",
					"path": [
						"currency"
					]
				}
			},
			"response": []
		},
		{
			"name": "7.Currency_byn",
			"request": {
				"method": "POST",
				"header": [],
				"body": {
					"mode": "formdata",
					"formdata": [
						{
							"key": "auth_token",
							"value": "\"/s34lfgbj/None/jjd909/70545kjkWpqc3406None253300evny\"",
							"type": "text"
						},
						{
							"key": "curr_code",
							"value": "145",
							"type": "text"
						}
					]
				},
				"url": {
					"raw": "http://116.203.27.46:5002/curr_byn",
					"protocol": "http",
					"host": [
						"116",
						"203",
						"27",
						"46"
					],
					"port": "5002",
					"path": [
						"curr_byn"
					]
				}
			},
			"response": []
		}
	]
}